redmed/__init__.py
redmed/redmedTagger.py
redmed/textHandler.py
redmed/data/redmed_drug_lexicon.tsv
redmed/data/redmed_phrases.txt
redmed-0.1.2.dist-info/LICENSE
redmed-0.1.2.dist-info/METADATA
redmed-0.1.2.dist-info/WHEEL
redmed-0.1.2.dist-info/top_level.txt
redmed-0.1.2.dist-info/RECORD
