Metadata-Version: 2.1
Name: redmed
Version: 0.1.2
Summary: Lexicon and associated tools for identifying drug mentions in social media data
Home-page: https://github.com/alavertu/redmed
Author: Adam Lavertu
Author-email: adamlavertu@gmail.com
License: UNKNOWN
Download-URL: https://github.com/alavertu/redmed.git
Keywords: pharmacovigilance,lexicon,text analysis,drugs,social media data
Platform: UNKNOWN
